{
  "title": "Sections",
  "routes": [
    {
      "title": "Overview",
      "hash": "overview",
      "properties": [
        "availableOnDevice",
        "doi",
        "featureList",
        "healthCondition",
        "infectiousAgent",
        "inLanguage",
        "input",
        "license",
        "locationNames",
        "measurementTechnique",
        "nctid",
        "output",
        "programmingLanguage",
        "softwareHelp",
        "softwareRequirements",
        "softwareVersion",
        "spatialCoverage",
        "species",
        "temporalCoverage",
        "topicCategory",
        "variableMeasured"
      ],
      "ui": {
        "isCollapsible": true,
        "showInNavigation": true,
        "showEmptyState": true
      }
    },
    {
      "title": "Keywords",
      "hash": "keywords",
      "properties": ["keywords"],
      "ui": {
        "isCollapsible": true,
        "showInNavigation": true
      }
    },
    {
      "title": "Application Categories",
      "hash": "applicationCategory",
      "properties": ["applicationCategory"],
      "ui": {
        "isCollapsible": true,
        "showInNavigation": true
      }
    },
    {
      "title": "Programming Languages",
      "hash": "programmingLanguage",
      "properties": ["programmingLanguage"],
      "ui": {
        "isCollapsible": true,
        "showInNavigation": true
      }
    },

    {
      "title": "Description",
      "hash": "description",
      "properties": ["description"],
      "ui": {
        "isCollapsible": true,
        "showInNavigation": true
      }
    },
    {
      "title": "Provenance",
      "hash": "provenance",
      "properties": ["includedInDataCatalog", "url", "sdPublisher"],
      "ui": {
        "isCollapsible": true,
        "showInNavigation": true,
        "showEmptyState": true
      }
    },
    {
      "title": "File Downloads",
      "hash": "downloads",
      "properties": ["distribution", "downloadUrl"],
      "ui": {
        "isCollapsible": true,
        "showInNavigation": true
      }
    },
    {
      "title": "Funding",
      "hash": "funding",
      "properties": ["funding"],
      "ui": {
        "isCollapsible": true,
        "showInNavigation": true,
        "showEmptyState": true
      }
    },
    {
      "title": "Based On",
      "hash": "isBasedOn",
      "properties": ["isBasedOn"],
      "ui": {
        "isCollapsible": true,
        "showInNavigation": true
      }
    },
    {
      "title": "Cited By",
      "hash": "citedBy",
      "properties": ["citedBy"],
      "ui": {
        "isCollapsible": true,
        "showInNavigation": true
      }
    },
    {
      "title": "Related Resources",
      "hash": "relatedResources",
      "properties": ["hasPart", "isBasisFor", "isRelatedTo", "isPartOf"],
      "ui": {
        "isCollapsible": true,
        "showInNavigation": true
      }
    },
    {
      "title": "Samples",
      "hash": "samples",
      "properties": ["sample.collectionSize", "sample.sampleQuantity"],
      "ui": {
        "isCollapsible": true,
        "showInNavigation": true,
        "showEmptyState": false
      }
    },
    {
      "title": "Metadata",
      "hash": "metadata",
      "properties": ["rawData"],
      "ui": {
        "isCollapsible": true,
        "showInNavigation": true
      }
    }
  ]
}
